audit_history/__init__.py
audit_history/apps.py
audit_history/fields.py
audit_history/mixins.py
audit_history/settings.py
audit_history/utils.py
audit_history/widgets.py
audit_history/templates/widget.html
django_model_audit_history-1.1.3.dist-info/DESCRIPTION.rst
django_model_audit_history-1.1.3.dist-info/METADATA
django_model_audit_history-1.1.3.dist-info/RECORD
django_model_audit_history-1.1.3.dist-info/WHEEL
django_model_audit_history-1.1.3.dist-info/metadata.json
django_model_audit_history-1.1.3.dist-info/top_level.txt
