Metadata-Version: 2.0
Name: django-model-audit-history
Version: 1.1.3
Summary: A Django model field for PostgreSQL to store changes to a model chronologically.
Home-page: https://github.com/nexto/django-model-audit-history
Author: Henrik Heimbuerger
Author-email: henrik@smileback.com
License: MIT License
Platform: UNKNOWN
Classifier: Environment :: Web Environment
Classifier: Framework :: Django
Classifier: Intended Audience :: Developers
Classifier: License :: OSI Approved :: MIT License
Classifier: Operating System :: OS Independent
Classifier: Programming Language :: Python
Classifier: Programming Language :: Python :: 2.7
Classifier: Programming Language :: Python :: 3.5
Classifier: Programming Language :: Python :: 3.6
Classifier: Topic :: Internet :: WWW/HTTP
Requires-Python: >=2.7, !=3.0.*, !=3.1.*, !=3.2.*, !=3.3.*, !=3.4.*
Requires-Dist: Django (<2.0)
Requires-Dist: ipaddress
Requires-Dist: six
